skykit/__init__.py
skykit/providers/__init__.py
skykit/providers/sentinel2.py
skykit/providers/families/__init__.py
skykit/providers/families/sentinel.py
skykit/utils/__init__.py
skykit/utils/geojson.py
skykit-0.1.3.dist-info/LICENSE.txt
skykit-0.1.3.dist-info/METADATA
skykit-0.1.3.dist-info/WHEEL
skykit-0.1.3.dist-info/top_level.txt
skykit-0.1.3.dist-info/RECORD
