Metadata-Version: 2.1
Name: skykit
Version: 0.1.3
Summary: Out-of-the-box methods for satellite imagery processing
Home-page: https://github.com/htaidirt/skykit
Author: Hassen Taidirt
Author-email: htaidirt@gmail.com
License: UNKNOWN
Platform: UNKNOWN
Classifier: Programming Language :: Python :: 3
Classifier: License :: OSI Approved :: MIT License
Classifier: Operating System :: OS Independent
Requires-Dist: sentinelsat
Provides-Extra: test
Requires-Dist: coverage ; extra == 'test'
Requires-Dist: pytest ; extra == 'test'
Requires-Dist: pytest-mock ; extra == 'test'
